pyd2lang_native-0.0.3.dist-info/RECORD
pyd2lang_native-0.0.3.dist-info/WHEEL
pyd2lang_native-0.0.3.dist-info/top_level.txt
pyd2lang_native-0.0.3.dist-info/METADATA
pyd2lang_native-0.0.3.dist-info/licenses/LICENSE
pyd2lang_native-0.0.3.dist-info/licenses/D2_LICENSE.txt
d2/__init__.py
d2/resources/d2lib.dylib
