Metadata-Version: 2.4
Name: pyd2lang-native
Version: 0.0.3
Summary: Python bindings to d2lang
Author-email: "Travis F. Collins" <travis.collins@analog.com>
Requires-Python: >=3.7
License-File: LICENSE
License-File: D2_LICENSE.txt
Dynamic: license-file
